{"UWRegID": "10000000000000000000000000006AB3", "DisplayName": "J Average 6AB3", "RegisteredFirstMiddleName": "Average", "PreferredMiddleName": "Average", "UIDNumber": "99689", "PreferredSurname": "6AB3", "RegisteredName": "J Average 6AB3", "IsTestEntity": false, "RegisteredSurname": "6AB3", "EduPersonAffiliations": ["alum"], "PriorUWRegIDs": [], "PersonAffiliations": {"StudentPersonAffiliation": {"StudentNumber": "8675309", "StudentSystemKey": "008675309", "StudentWhitePages": {"PublishInDirectory": false, "Name": null, "Class": null, "Phone": null, "Departments": [], "Email": "javg6ab3@uw.edu"}}, "EmployeePersonAffiliation": {"HomeDepartment": "COMPUTER SCIENCE & ENG", "MailStop": "8675309", "EmployeeID": "8675309", "EmployeeWhitePages": {"TouchDials": [], "Department1": null, "Department2": null, "EmailAddresses": ["javg6ab3@uw.edu", "javg6ab3@uw.edu"], "PublishInDirectory": false, "Pagers": [], "Faxes": [], "Title1": null, "Title2": null, "Mobiles": [], "Name": null, "Positions": [], "VoiceMails": [], "Addresses": [], "Phones": []}}}, "PreferredFirstName": "J", "WhitepagesPublish": false, "PriorUWNetIDs": [], "UWNetID": "javg6ab3"}
