{"UWRegID": "1000000000000000000000000000D691", "DisplayName": "J Average D691", "RegisteredFirstMiddleName": "Average", "PreferredMiddleName": "Average", "UIDNumber": "372797", "PreferredSurname": "D691", "RegisteredName": "J Average D691", "IsTestEntity": false, "RegisteredSurname": "D691", "EduPersonAffiliations": ["alum"], "PriorUWRegIDs": [], "PersonAffiliations": {"StudentPersonAffiliation": {"StudentNumber": "8675309", "StudentSystemKey": "008675309", "StudentWhitePages": {"PublishInDirectory": false, "Name": null, "Class": null, "Phone": null, "Departments": [], "Email": "javgd691@uw.edu"}}, "EmployeePersonAffiliation": {"HomeDepartment": "PHARMACOLOGY", "MailStop": "8675309", "EmployeeID": "8675309", "EmployeeWhitePages": {"TouchDials": [], "Department1": null, "Department2": null, "EmailAddresses": ["javgd691@uw.edu", "javgd691@uw.edu"], "PublishInDirectory": false, "Pagers": [], "Faxes": [], "Title1": null, "Title2": null, "Mobiles": [], "Name": null, "Positions": [], "VoiceMails": [], "Addresses": [], "Phones": []}}}, "PreferredFirstName": "J", "WhitepagesPublish": false, "PriorUWNetIDs": [], "UWNetID": "javgd691"}
