{"DisplayName":"J Average 0B2C","EduPersonAffiliations":["alum"],"IsTestEntity":false,"PriorUWNetIDs":[],"PriorUWRegIDs":[],"RegisteredFirstMiddleName":"Average","RegisteredName":"J Average 0B2C","RegisteredSurname":"0B2C","UIDNumber":"343934","UWNetID":"javg0b2c","UWRegID":"10000000000000000000000000000B2C","WhitepagesPublish":false,"PersonAffiliations":{"EmployeePersonAffiliation":{"EmployeeID":"8675309","EmployeeWhitePages":{"Address1":null,"Address2":null,"Department1":null,"Department2":null,"Email1":"javg0b2c@uw.edu","Email2":"javg0b2c@uw.edu","Fax":null,"Name":null,"Phone1":null,"Phone2":null,"PublishInDirectory":false,"Title1":null,"Title2":null,"TouchDial":null,"VoiceMail":null},"HomeDepartment":"UW ALUMNI GOF","MailStop":"8675309"},"StudentPersonAffiliation":{"StudentNumber":"8675309","StudentSystemKey":"008675309","StudentWhitePages":{"Class":null,"Department1":null,"Department2":null,"Department3":null,"Email":"javg0b2c@uw.edu","Name":null,"Phone":null,"PublishInDirectory":false}}}}