{"DisplayName":"J Average CF4D","EduPersonAffiliations":["alum"],"IsTestEntity":false,"PriorUWNetIDs":[],"PriorUWRegIDs":[],"RegisteredFirstMiddleName":"Average","RegisteredName":"J Average CF4D","RegisteredSurname":"CF4D","UIDNumber":"402920","UWNetID":"javgcf4d","UWRegID":"1000000000000000000000000000CF4D","WhitepagesPublish":false,"PersonAffiliations":{"StudentPersonAffiliation":{"StudentNumber":"8675309","StudentSystemKey":"008675309","StudentWhitePages":{"Class":null,"Department1":null,"Department2":null,"Department3":null,"Email":"javgcf4d@uw.edu","Name":null,"Phone":null,"PublishInDirectory":false}}}}