{"DisplayName":"J Average 9FDC","EduPersonAffiliations":["alum"],"IsTestEntity":false,"PriorUWNetIDs":[],"PriorUWRegIDs":[],"RegisteredFirstMiddleName":"Average","RegisteredName":"J Average 9FDC","RegisteredSurname":"9FDC","UIDNumber":"459760","UWNetID":"javg9fdc","UWRegID":"10000000000000000000000000009FDC","WhitepagesPublish":false,"PersonAffiliations":{"StudentPersonAffiliation":{"StudentNumber":"8675309","StudentSystemKey":"008675309","StudentWhitePages":{"Class":null,"Department1":null,"Department2":null,"Department3":null,"Email":"javg9fdc@uw.edu","Name":null,"Phone":null,"PublishInDirectory":false}}}}