{"UWRegID": "1000000000000000000000000000F0EC", "DisplayName": "J Average F0EC", "RegisteredFirstMiddleName": "Average", "PreferredMiddleName": "Average", "UIDNumber": "459305", "PreferredSurname": "F0EC", "RegisteredName": "J Average F0EC", "IsTestEntity": false, "RegisteredSurname": "F0EC", "EduPersonAffiliations": ["member", "student", "alum"], "PriorUWRegIDs": [], "PersonAffiliations": {"StudentPersonAffiliation": {"StudentNumber": "8675309", "StudentSystemKey": "008675309", "StudentWhitePages": {"PublishInDirectory": true, "Name": "J Average F0EC", "Class": "1st Yr Prof", "Phone": "1 555 555-1234", "Departments": ["Law"], "Email": "javgf0ec@uw.edu"}}}, "PreferredFirstName": "J", "WhitepagesPublish": true, "PriorUWNetIDs": [], "UWNetID": "javgf0ec"}
