{"StudentName": "J Average 40DF", "FirstName": "J Average", "LastName": "40DF", "Veteran": {"Code": "0", "Description": "NOT A VET"}, "Sports": [], "LastEnrolled": {"Quarter": "winter", "Href": "/student/v5/term/2014,winter.json", "Year": 2014}, "Notices": {"RegID": "100000000000000000000000000040DF", "Href": "/student/v5/notice/100000000000000000000000000040DF.json"}, "PersonFinancial": {"RegID": "100000000000000000000000000040DF", "Href": "/student/v5/person/100000000000000000000000000040DF/financial.json"}, "Email": "40DF@uw.ed", "ResidencyDescription": "RESIDENT", "Metadata": null, "DirectoryRelease": true, "StudentSystemKey": "55545559", "BirthDate": "1984-01-01", "RegisteredName": "J Average 40DF", "Gender": "F", "RegID": "100000000000000000000000000040DF", "StudentNumber": "0000001", "VisaType": "", "LocalPhone": "5558675309", "LocalAddress": {"City": "SEATTLE", "Zip": "89121", "Country": "", "Line2": "APT 302", "Line1": "555 W DEMOCRAT ST", "State": "WA", "PostalCode": ""}, "TestScore": {"RegID": "100000000000000000000000000040DF", "Href": "/student/v5/testscore/100000000000000000000000000040DF.json"}, "RepositoryTimeStamp": null, "PermanentAddress": {"City": "SEATTLE", "Zip": "89121", "Country": "", "Line2": "", "Line1": "555 W DEMOCRAT ST APT 007", "State": "WA", "PostalCode": ""}, "PermanentPhone": "5558675309", "EmployeeID": null, "Resident": "1", "UWNetID": "40DF", "CurrentEnrollment": null}