{"DisplayName":"J Average 33A2","EduPersonAffiliations":["alum"],"IsTestEntity":false,"PriorUWNetIDs":[],"PriorUWRegIDs":[],"RegisteredFirstMiddleName":"Average","RegisteredName":"J Average 33A2","RegisteredSurname":"33A2","UIDNumber":"448859","UWNetID":"javg33a2","UWRegID":"100000000000000000000000000033A2","WhitepagesPublish":false,"PersonAffiliations":{"StudentPersonAffiliation":{"StudentNumber":"8675309","StudentSystemKey":"008675309","StudentWhitePages":{"Class":null,"Department1":null,"Department2":null,"Department3":null,"Email":"javg33a2@uw.edu","Name":null,"Phone":null,"PublishInDirectory":false}}}}