{"UWRegID": "10000000000000000000000000008CE4", "DisplayName": "J Average 8CE4", "RegisteredFirstMiddleName": "Average", "PreferredMiddleName": "Average", "UIDNumber": "577563", "PreferredSurname": "8CE4", "RegisteredName": "J Average 8CE4", "IsTestEntity": false, "RegisteredSurname": "8CE4", "EduPersonAffiliations": ["alum"], "PriorUWRegIDs": [], "PersonAffiliations": {"StudentPersonAffiliation": {"StudentNumber": "8675309", "StudentSystemKey": "008675309", "StudentWhitePages": {"PublishInDirectory": false, "Name": null, "Class": null, "Phone": null, "Departments": [], "Email": "javg8ce4@uw.edu"}}}, "PreferredFirstName": "J", "WhitepagesPublish": false, "PriorUWNetIDs": [], "UWNetID": "javg8ce4"}
