{"DisplayName":"J Average 938E","EduPersonAffiliations":["member","alum","staff","employee"],"IsTestEntity":false,"PriorUWNetIDs":[],"PriorUWRegIDs":[],"RegisteredFirstMiddleName":"Average","RegisteredName":"J Average 938E","RegisteredSurname":"938E","UIDNumber":"452337","UWNetID":"javg938e","UWRegID":"1000000000000000000000000000938E","WhitepagesPublish":true,"PersonAffiliations":{"EmployeePersonAffiliation":{"EmployeeID":"8675309","EmployeeWhitePages":{"Address1":null,"Address2":null,"Department1":"ENG: Electrical Engineering-Staff","Department2":null,"Email1":"javg938e@uw.edu","Email2":"javg938e@uw.edu","Fax":null,"Name":"J Average 938E","Phone1":"1 555 555-1234","Phone2":null,"PublishInDirectory":true,"Title1":"Budget\/Fiscal Analyst","Title2":null,"TouchDial":null,"VoiceMail":null},"HomeDepartment":"ENG: Electrical Engineering-Staff","MailStop":"8675309"},"StudentPersonAffiliation":{"StudentNumber":"8675309","StudentSystemKey":"008675309","StudentWhitePages":{"Class":null,"Department1":null,"Department2":null,"Department3":null,"Email":"javg938e@uw.edu","Name":null,"Phone":null,"PublishInDirectory":false}}}}