{"UWRegID": "1000000000000000000000000000E1F0", "DisplayName": "J Average E1F0", "RegisteredFirstMiddleName": "Average", "PreferredMiddleName": "Average", "UIDNumber": "444788", "PreferredSurname": "E1F0", "RegisteredName": "J Average E1F0", "IsTestEntity": false, "RegisteredSurname": "E1F0", "EduPersonAffiliations": ["alum"], "PriorUWRegIDs": [], "PersonAffiliations": {"StudentPersonAffiliation": {"StudentNumber": "8675309", "StudentSystemKey": "008675309", "StudentWhitePages": {"PublishInDirectory": false, "Name": null, "Class": null, "Phone": null, "Departments": [], "Email": "javge1f0@uw.edu"}}, "EmployeePersonAffiliation": {"HomeDepartment": "DEAN EDUCATION", "MailStop": "8675309", "EmployeeID": "8675309", "EmployeeWhitePages": {"TouchDials": [], "Department1": null, "Department2": null, "EmailAddresses": ["javge1f0@uw.edu", "javge1f0@uw.edu"], "PublishInDirectory": false, "Pagers": [], "Faxes": [], "Title1": null, "Title2": null, "Mobiles": [], "Name": null, "Positions": [], "VoiceMails": [], "Addresses": [], "Phones": []}}}, "PreferredFirstName": "J", "WhitepagesPublish": false, "PriorUWNetIDs": [], "UWNetID": "javge1f0"}
