{"DisplayName":"J Average BA89","EduPersonAffiliations":["member","student","alum"],"IsTestEntity":false,"PriorUWNetIDs":[],"PriorUWRegIDs":[],"RegisteredFirstMiddleName":"Average","RegisteredName":"J Average BA89","RegisteredSurname":"BA89","UIDNumber":"448200","UWNetID":"javgba89","UWRegID":"1000000000000000000000000000BA89","WhitepagesPublish":false,"PersonAffiliations":{"StudentPersonAffiliation":{"StudentNumber":"8675309","StudentSystemKey":"008675309","StudentWhitePages":{"Class":null,"Department1":null,"Department2":null,"Department3":null,"Email":"javgba89@uw.edu","Name":null,"Phone":null,"PublishInDirectory":false}}}}